{
  "solution": {
    "ember-primitives": {
      "impact": "minor",
      "oldVersion": "0.34.0",
      "newVersion": "0.35.0",
      "tagName": "latest",
      "constraints": [
        {
          "impact": "minor",
          "reason": "Appears in changelog section :rocket: Enhancement"
        }
      ],
      "pkgJSONPath": "./ember-primitives/package.json"
    }
  },
  "description": "## Release (2025-07-11)\n\n* ember-primitives 0.35.0 (minor)\n\n#### :rocket: Enhancement\n* `ember-primitives`\n  * [#502](https://github.com/universal-ember/ember-primitives/pull/502) New utility component: In-head ([@NullVoxPopuli](https://github.com/NullVoxPopuli))\n\n#### Committers: 1\n- [@NullVoxPopuli](https://github.com/NullVoxPopuli)\n"
}
